{
  "時間が開く": "(じかんがあく) - to have time free; to have time to spare",
  "時間ずれ": "(じかんずれ) - time deviation; time lag; jitter",
  "時間つぶし": "(じかんつぶし) - timewasting; killing time",
  "時間どおり": "(じかんどおり) - on time",
  "時間どおりに": "(じかんどおりに) - punctually; on time; as regularly as a clock",
  "時間に遅れる": "(じかんにおくれる) - to be late; to be unpunctual",
  "時間のたつ": "(じかんのたつ) - passage of time; perceived time; relative time",
  "時間のムダ": "(じかんのムダ) - waste of time",
  "時間の問題": "(じかんのもんだい) - a matter of time; matter of hours; question of time",
  "時間の歪み": "(じかんのひずみ) - time warp",
  "時間の無駄": "(じかんのむだ) - waste of time",
  "時間の許す限り": "(じかんのゆるすかぎり) - as long as time allows",
  "時間をかける": "(じかんをかける) - to spend time (on doing something)",
  "時間をつぶす": "(じかんをつぶす) - to kill time",
  "時間をむだにする": "(じかんをむだにする) - to waste time",
  "時間を割く": "(じかんをさく) - to spare time (for)",
  "時間を守る": "(じかんをまもる) - to be punctual",
  "時間を守る人": "(じかんをまもるひと) - punctual person",
  "時間を惜しむ": "(じかんをおしむ) - to value time",
  "時間を掛ける": "(じかんをかける) - to spend time (on doing something)",
  "時間を潰す": "(じかんをつぶす) - to kill time",
  "時間を無駄にする": "(じかんをむだにする) - to waste time",
  "時間を稼ぐ": "(じかんをかせぐ) - to gain time",
  "時間を空ける": "(じかんをあける) - to make oneself available (free)",
  "時間係審判": "(じかんがかりしんぱん) - {sumo} judge timing the matches",
  "時間分割多元接続方式": "(じかんぶんかつたげんせつぞくほうしき) - TDMA; time division multiple access",
  "時間切れ": "(じかんぎれ) - being out of time/passing the deadline; time-out",
  "時間別": "(じかんべつ) - differentiated by time",
  "時間刻み": "(じかんきざみ) - clock tick",
  "時間割": "(じかんわり) - timetable (esp. a weekly school timetable); schedule",
  "時間割り": "(じかんわり) - timetable (esp. a weekly school timetable); schedule",
  "時間割りを直す": "(じかんわりをなおす) - to alter the schedule",
  "時間効果": "(じかんこうか) - time effect",
  "時間反転": "(じかんはんてん) - time reversal",
  "時間変換係数": "(じかんへんかんけいすう) - time scale (factor)",
  "時間外": "(じかんがい) - overtime; outside of hours (school, office, surgery, etc.)",
  "時間外労働": "(じかんがいろうどう) - overtime work",
  "時間外手当て": "(じかんがいてあて) - overtime pay",
  "時間多重": "(じかんたじゅう) - TDD; time division duplex",
  "時間帯": "(じかんたい) - period of time; time slot; time zone",
  "時間待ち": "(じかんまち) - lay-over; stop-over",
  "時間性": "(じかんせい) - temporality",
  "時間旅行": "(じかんりょこう) - time travel",
  "時間潰し": "(じかんつぶし) - timewasting; killing time",
  "時間生物学": "(じかんせいぶつがく) - chronobiology",
  "時間発展": "(じかんはってん) - time evolution; temporal development",
  "時間的": "(じかんてき) - timewise; temporal; chronal",
  "時間目": "(じかんめ) - period (e.g. class)",
  "時間知覚": "(じかんちかく) - time perception; chronognosis",
  "時間稼ぎ": "(じかんかせぎ) - holding out; stalling; putting off; time-buying",
  "時間節約": "(じかんせつやく) - time preservation; saving time",
  "時間給": "(じかんきゅう) - hourly pay; hourly wage",
  "時間芸術": "(じかんげいじゅつ) - temporal art; art forms which unfold over time",
  "時間表": "(じかんひょう) - time-table; allocation of time (e.g. to tasks)/time usage",
  "時間貸し": "(じかんかし) - pay by the hour (parking)",
  "時間転移": "(じかんてんい) - time warp",
  "時間軸": "(じかんじく) - time axis",
  "時間通り": "(じかんどおり) - on time",
  "時間通りに": "(じかんどおりに) - punctually; on time; as regularly as a clock",
  "時間選好": "(じかんせんこう) - time preference",
  "時間順序積": "(じかんじゅんじょせき) - time ordered product",
  "時限": "(じげん) - (school) period; period or division of time/time limit",
  "時限スト": "(じげんスト) - time-limited strike",
  "時限ストライキ": "(じげんストライキ) - time-limited strike",
  "時限爆弾": "(じげんばくだん) - time bomb",
  "時限目": "(じげんめ) - period of time",
  "時限立法": "(じげんりっぽう) - temporary legislation; legislation with a specified duration; act valid for a limited time",
  "時限装置": "(じげんそうち) - timing device",
  "時雨": "(じう) - drizzle/shower in late autumn (fall) or early winter; (じう only) seasonable rain",
  "時雨の化": "(じうのか) - benevolent rule of a gracious sovereign",
  "時雨忌": "(しぐれき) - Matsuo Basho remembrance day (12th day of the 10th lunar month, associated with the change of the seasons)",
  "時雨月": "(しぐれづき) - tenth lunar month",
  "時雨模様": "(しぐれもよう) - (yoji) showery sky; (it is) looking showery",
  "時雨煮": "(しぐれに) - seafood, etc. preserve made with mirin, ginger and soy",
  "時鳥": "(ホトトギス) - lesser cuckoo (Cuculus poliocephalus)",
  "時鳥草": "(ホトトギスソウ) - toad lily (Tricyrtis hirta)",
  "晃々": "(こうこう) - brilliant; dazzling; light; bright",
  "晃晃": "(こうこう) - brilliant; dazzling; light; bright",
  "晃曜": "(こうよう) - dazzling brightness",
  "晃朗": "(こうろう) - bright and brilliant",
  "晋": "(しん) - Advance , Jin dynasty (China, 265-420), Chin dynasty",
  "晋山": "(しんざん) - taking up a new position as chief priest of a Buddhist temple",
  "晋書": "(しんじょ) - History of the Jin Dynasty",
  "晏如": "(あんじょ) - calm; tranquil",
  "晏然": "(あんぜん) - calm; tranquil",
  "晒": "(さい) - Alvejante",
  "晒し": "(さらし) - bleaching; bleached cotton",
  "晒し木綿": "(さらしもめん) - bleached cotton cloth",
  "晒し粉": "(さらしこ) - bleaching powder",
  "晒し者": "(さらしもの) - pilloried criminal exposed to public view; public scorn or humiliation; person shamed in front of others",
  "晒し裏": "(さらしうら) - bleached lining (esp. tabi); bleached interior",
  "晒し飴": "(さらしあめ) - sweet rice jelly; (whitish) rice candy",
  "晒し首": "(さらしくび) - criminal's head on public display; displaying a beheaded head; beheaded head",
  "晒す": "(さらす) - to expose (to the air, to the public, to danger, etc.); to bleach/to refine",
  "晒木綿": "(さらしもめん) - bleached cotton cloth",
  "晒者": "(さらしもの) - pilloried criminal exposed to public view; public scorn or humiliation; person shamed in front of others",
  "晒裏": "(さらしうら) - bleached lining (esp. tabi); bleached interior",
  "晒首": "(さらしくび) - criminal's head on public display; displaying a beheaded head; beheaded head",
  "晝": "(ちゅう) - Durante o dia",
  "晦": "(かい) - Escuro"
}