{
  "超訳": "(ちょうやく) - super-liberal interpretation; making understandable, readable through free interpretation",
  "超豪華": "(ちょうごうか) - ultra-luxurious; lavish",
  "超超大規模集積回路": "(ちょうちょうだいきぼしゅうせきかいろ) - ultra large-scale integration; ULSI",
  "超越": "(chouetsu) - transcendência, transcendência; transcendental, transcendência, transcendência; transcendental; transcender, superar",
  "超越主義": "(ちょうえつしゅぎ) - transcendentalism",
  "超越交代": "(ちょうえつこうたい) - passage of lines",
  "超越数": "(ちょうえつすう) - transcendental number",
  "超越数論": "(ちょうえつすうろん) - transcendental number theory",
  "超越点": "(ちょうえつてん) - passage point",
  "超越的": "(ちょうえつてき) - transcendental",
  "超越神": "(ちょうえつじん) - transcendental deity",
  "超越論的": "(ちょうえつろんてき) - transcendental",
  "超越論的意識": "(ちょうえつろんてきいしき) - transcendental consciousness",
  "超越論的方法": "(ちょうえつろんてきほうほう) - transcendental method",
  "超越論的観念論": "(ちょうえつろんてきかんねんろん) - transcendental idealism",
  "超越関数": "(ちょうえつかんすう) - transcendental function",
  "超軽量": "(ちょうけいりょう) - ultralight; ultralightweight",
  "超連結子": "(ちょうれんけつし) - hyperlink",
  "超過": "(chouka) - excesso, sendo mais do que",
  "超過保険": "(ちょうかほけん) - overinsurance",
  "超過分": "(ちょうかぶん) - surplus; excess",
  "超過利潤": "(ちょうかりじゅん) - excess profit",
  "超過勤務": "(ちょうかきんむ) - overtime (work)",
  "超過勤務手当": "(ちょうかきんむてあて) - overtime pay",
  "超過情報速度": "(ちょうかじょうほうそくど) - excess information rate",
  "超過課税": "(ちょうかかぜい) - excessive taxation",
  "超過送信": "(ちょうかそうしん) - jabber",
  "超過送信制御": "(ちょうかそうしんせいぎょ) - jabber control",
  "超過額": "(ちょうかがく) - a surplus; an excess",
  "超遠心機": "(ちょうえんしんき) - ultracentrifuge",
  "超酸": "(ちょうさん) - superacid",
  "超重元素": "(ちょうじゅうげんそ) - transuranium element; transuranic element; super heavy element",
  "超重核": "(ちょうじゅうかく) - superheavy nucleus; ultraheavy nucleus",
  "超重質油": "(ちょうじゅうしつゆ) - extra heavy oil; heavy crude oil",
  "超銀河団": "(ちょうぎんがだん) - supercluster of galaxies",
  "超銀河集団": "(ちょうぎんがしゅうだん) - supercluster of galaxies",
  "超長波": "(ちょうちょうは) - very low frequency wave; VLF wave",
  "超長距離干渉計": "(ちょうちょうきょりかんしょうけい) - {astron} very long baseline interferometry; VLBI",
  "超限": "(ちょうげん) - transfinite",
  "超限帰納法": "(ちょうげんきのうほう) - transfinite induction",
  "超限数": "(ちょうげんすう) - transfinite number",
  "超電導": "(ちょうでんどう) - superconductivity; super-conductivity",
  "超電導磁気浮上式鉄道": "(ちょうでんどうじきふじょうしきてつどう) - superconducting maglev train",
  "超音波": "(ちょうおんぱ) - ultrasonic waves; ultrasound",
  "超音波モーター": "(ちょうおんぱモーター) - ultrasonic motor",
  "超音波処理": "(ちょうおんぱしょり) - ultrasonication; sonication; ultrasonic treatment",
  "超音波探傷器": "(ちょうおんぱたんしょうき) - ultrasonic test instrument",
  "超音波探傷装置": "(ちょうおんぱたんしょうそうち) - ultrasonic test equipment",
  "超音波検査": "(ちょうおんぱけんさ) - ultrasound examination",
  "超音波検査法": "(ちょうおんぱけんさほう) - sonography; ultrasonography",
  "超音波洗浄": "(ちょうおんぱせんじょう) - ultrasonic cleaning",
  "超音波発生装置": "(ちょうおんぱはっせいそうち) - ultrasonic generator; sonicator",
  "超音波顕微鏡": "(ちょうおんぱけんびきょう) - ultrasonic microscope; acoustic microscope",
  "超音速": "(ちょうおんそく) - supersonic speed",
  "超音速旅客機": "(ちょうおんそくりょかくき) - supersonic airliner (i.e. the Concorde)",
  "超音速機": "(ちょうおんそくき) - supersonic aircraft; supersonic plane",
  "超音速流": "(ちょうおんそくりゅう) - supersonic flow",
  "超音速輸送機": "(ちょうおんそくゆそうき) - supersonic transport; SST",
  "超高": "(ちょうこう) - extra-high; ultra; super",
  "超高圧送電": "(ちょうこうあつそうでん) - extra-high-voltage power transmission",
  "超高層": "(ちょうこうそう) - extreme height; high-rise (i.e. building)",
  "超高層ビル": "(ちょうこうそうビル) - skyscraper",
  "超高層建築": "(ちょうこうそうけんちく) - skyscraper",
  "超高層雷放電": "(ちょうこうそうかみなりほうでん) - upper-atmospheric lightning; upper-atmospheric discharge",
  "超高真空": "(ちょうこうしんくう) - ultra-high vacuum; UHV; extremely high vacuum; XHV",
  "超高純度": "(ちょうこうじゅんど) - ultrahigh purity",
  "超高負荷容量": "(ちょうこうふかようりょう) - ultrahigh load-carrying capacity; ultrahigh load capacity",
  "超高速": "(ちょうこうそく) - ultra high speed",
  "超高速並列インターフェース": "(ちょうこうそくへいれつインターフェース) - HIPPI; High Performance Parallel Interface",
  "超高速度": "(ちょうこうそくど) - super-high speed",
  "超高速度撮影": "(ちょうこうそくどさつえい) - high-speed photography",
  "超高齢化社会": "(ちょうこうれいかしゃかい) - (super) ageing society",
  "越える": "(こえる) - (esp. 越える) to cross over/to cross/to pass through/to pass over (out of); (esp. 超える) to exceed",
  "越し": "(goshi) - através de, sobre, além de, através, cruzando; ao longo de (um período de tempo), por",
  "越し屋根": "(こしやね) - roof monitor; monitor roof; lantern (roof)",
  "越す": "(こす) - to cross over (e.g. mountain)/to go across; to go over (e.g. with audience); to pass time (e.g. a winter); (often 超す) to surpass/to be better than/to exceed; to move house; to go/to come",
  "越中ふんどし": "(えっちゅうふんどし) - string loincloth; G-string",
  "越中褌": "(えっちゅうふんどし) - string loincloth; G-string",
  "越光": "(コシヒカリ) - Koshihikari (variety of rice)",
  "越冬": "(えっとう) - passing the winter; hibernation",
  "越冬地": "(えっとうち) - wintering spot (i.e. of a migrating bird)",
  "越冬資金": "(えっとうしきん) - winter bonus",
  "越冬隊": "(えっとうたい) - wintering party (team)",
  "越前水母": "(えちぜんくらげ) - Nomura's jellyfish (Nemopilema nomurai)",
  "越南": "(ベトナム) - Vietnam",
  "越境": "(えっきょう) - border transgression",
  "越境入学": "(えっきょうにゅうがく) - (yoji) gaining admission into a school in a school district other than one's own",
  "越天楽": "(えてんらく) - Etenraku (Japanese court music composition)",
  "越屋根": "(こしやね) - roof monitor; monitor roof; lantern (roof)",
  "越年": "(えつねん) - ring out the old year; hibernation",
  "越年生植物": "(えつねんせいしょくぶつ) - {bot}  winter annual; biennial; biennial plant",
  "越年草": "(えつねんそう) - {bot} winter annual; biennial; biennial plant",
  "越年草本": "(えつねんそうほん) - biennial herb",
  "越年蝶": "(オツネンチョウ) - eastern pale clouded yellow (butterfly, Colias erate)",
  "越幾斯": "(エキス) - extract (esp. of food, fruit, etc.); essence",
  "越度": "(おちど) - mistake; error; fault; slip; blunder; omission; oversight; lapse",
  "越後": "(えちご) - Echigo; old name for Niigata Prefecture",
  "越後兎": "(エチゴウサギ) - Lepus brachyurus lyoni (subspecies of Japanese hare)",
  "越後獅子": "(えちごじし) - street performance by itinerant entertainers featuring a tumbling act in which a child performer wears a carved lion's head",
  "越権": "(えっけん) - going beyond authority; unauthorized; unauthorised; ultra vires"
}