{
  "重箱の隅を突く": "(じゅうばこのすみをつつく) - to nitpick; to complain about trifles",
  "重箱読": "(じゅうばこよみ) - mixed on-kun reading",
  "重箱読み": "(じゅうばこよみ) - mixed on-kun reading",
  "重篤": "(じゅうとく) - serious (illness)",
  "重粒子": "(じゅうりゅうし) - baryon",
  "重縁": "(じゅうえん) - double marriage (in the same family); intermarriage",
  "重罪": "(じゅうざい) - felony; serious crime",
  "重罰": "(じゅうばつ) - heavy punishment",
  "重聴": "(じゅうちょう) - hard of hearing",
  "重職": "(じゅうしょく) - responsible position",
  "重臣": "(じゅうしん) - chief vassal; senior statesman",
  "重苦": "(じゅうく) - intense suffering",
  "重苦しい": "(おもくるしい) - heavy; gloomy; awkward; cumbrous; oppressive; leaden",
  "重荷": "(じゅうか) - load; heavy burden; encumbrance; heavy freight; heavy responsibility",
  "重装備": "(じゅうそうび) - heavy equipment; heavily equipped/heavily armed/heavily armored/heavily armoured",
  "重複": "(ちょうふく) - duplication; repetition; overlapping; redundancy; restoration",
  "重複保険": "(じゅうふくほけん) - double insurance",
  "重複名解決フラグ": "(じゅうふくめいかいけつフラグ) - conflict resolution flag",
  "重複感染": "(ちょうふくかんせん) - superinfection",
  "重複母音": "(じゅうふくぼいん) - geminate vowel",
  "重複立候補": "(じゅうふくりっこうほ) - simultaneously running for a seat in a single-member constituency and a seat in a proportionally representated constituency",
  "重複遺伝子": "(じゅうふくいでんし) - duplicated gene",
  "重複部分配列": "(じゅうふくぶぶんはいれつ) - many-one array section",
  "重要": "(juuyou) - importante, significativo, essencial, principal, grande",
  "重要なＳＧＭＬ文字": "(じゅうようなエスジーエムエルもじ) - significant SGML character",
  "重要事項": "(じゅうようじこう) - important matter; matters of weight",
  "重要人物": "(じゅうようじんぶつ) - important person; strategic person; key figure",
  "重要参考人": "(じゅうようさんこうにん) - material witness; suspect",
  "重要度": "(じゅうようど) - importance; priority",
  "重要度表示": "(じゅうようどひょうじ) - importance indication",
  "重要性": "(じゅうようせい) - importance; gravity",
  "重要文化財": "(じゅうようぶんかざい) - important cultural property; important cultural asset",
  "重要書類": "(じゅうようしょるい) - important documents; important papers",
  "重要案件": "(じゅうようあんけん) - (yoji) important matter (for discussion (deliberations))",
  "重要法案": "(じゅうようほうあん) - {law} important bill; key bill",
  "重要無形文化財": "(じゅうようむけいぶんかざい) - important intangible cultural asset",
  "重要無形民俗文化財": "(じゅうようむけいみんぞくぶんかざい) - important intangible folk culture asset",
  "重要産業": "(じゅうようさんぎょう) - key industry",
  "重要視": "(じゅうようし) - regarding highly; attaching importance to",
  "重視": "(じゅうし) - importance/stress/serious consideration; to take something seriously/to attach importance/to stress",
  "重視型": "(じゅうしがた) - oriented",
  "重言": "(じゅうごん) - succession of words of similar meaning",
  "重言葉": "(かさねことば) - repeated word or phrase; redundant wording; succession of words of similar meaning; pleonasm",
  "重訳": "(じゅうやく) - retranslation",
  "重詞": "(かさねことば) - repeated word or phrase; redundant wording; succession of words of similar meaning; pleonasm",
  "重詰": "(じゅうづめ) - food packed in nest of lacquered boxes",
  "重詰め": "(じゅうづめ) - food packed in nest of lacquered boxes",
  "重説": "(じゅうせつ) - reexplanation",
  "重謹慎": "(じゅうきんしん) - close confinement (in one's barracks)",
  "重責": "(じゅうせき) - heavy responsibility",
  "重賞": "(ちょうしょう) - large prize (e.g. in horse racing); generous reward",
  "重賞レース": "(じゅうしょうレース) - graded race (in horse-racing); high-stakes race",
  "重質": "(じゅうしつ) - heavy (esp. in oil, chemstry, etc.)",
  "重質油": "(じゅうしつゆ) - heavy oil",
  "重軌条": "(じゅうきじょう) - heavy rail",
  "重軽傷": "(じゅうけいしょう) - major or minor injuries",
  "重軽傷者": "(じゅうけいしょうしゃ) - those injured; injured persons; the wounded",
  "重農主義": "(じゅうのうしゅぎ) - physiocracy",
  "重農主義者": "(じゅうのうしゅぎしゃ) - physiocrat",
  "重酸素": "(じゅうさんそ) - heavy oxygen",
  "重重": "(じゅうじゅう) - repeated; manifold",
  "重重しい": "(おもおもしい) - serious; grave; dignified; solemn",
  "重重に": "(じゅうじゅうに) - extremely",
  "重重にも": "(じゅうじゅうにも) - repeatedly",
  "重量": "(じゅうりょう) - weight; heavyweight boxer",
  "重量エネルギー密度": "(じゅうりょうエネルギーみつど) - specific energy (Wh-kg)",
  "重量トン": "(じゅうりょうトン) - deadweight ton; deadweight tonnage",
  "重量ポンド": "(じゅうりょうポンド) - pound-force",
  "重量上げ": "(じゅうりょうあげ) - weight lifting",
  "重量分析": "(じゅうりょうぶんせき) - gravimetric analysis",
  "重量制限": "(じゅうりょうせいげん) - weight restriction; weight limit",
  "重量噸": "(じゅうりょうとん) - dead-weight tonnage",
  "重量噸数": "(じゅうりょうとんすう) - dead-weight tonnage",
  "重量感": "(じゅうりょうかん) - thick and heavy",
  "重量感覚": "(じゅうりょうかんかく) - sense of weight",
  "重量拳闘選手": "(じゅうりょうけんとうせんしゅ) - heavy weight boxer",
  "重量挙げ": "(じゅうりょうあげ) - weight lifting",
  "重量法": "(じゅうりょうほう) - gravimetric method",
  "重量級": "(じゅうりょうきゅう) - heavyweight class",
  "重量選手": "(じゅうりょうせんしゅ) - heavyweight player",
  "重金主義": "(じゅうきんしゅぎ) - bullionism",
  "重金属": "(じゅうきんぞく) - heavy metals",
  "重鎮": "(juuchin) - líder, autoridade, pilar",
  "重陽": "(ちょうよう) - Chrysanthemum Festival (the 9th day of the 9th lunar month) (one of the five annual festivals)",
  "重陽子": "(じゅうようし) - deuteron",
  "重電": "(じゅうでん) - heavy electric; heavy electric machinery",
  "重電機": "(じゅうでんき) - heavy electric equipment",
  "重電機器": "(じゅうでんきき) - heavy electrical machinery",
  "重電気": "(じゅうでんき) - heavy electric (power)",
  "重馬場": "(おもばば) - muddy track (in horse racing); dead track",
  "重騎兵": "(じゅうきへい) - heavy cavalry",
  "野": "(sim/não) - field , plain, field; hidden (structural) member; wild; lacking a political post",
  "野いちご": "(ノイチゴ) - wild strawberry (Fragaria vesca)",
  "野ざらし": "(のざらし) - weather-beaten",
  "野となれ山となれ": "(のとなれやまとなれ) - I don't care what happens (after this)",
  "野に下る": "(やにくだる) - to leave the government service",
  "野に在る": "(やにある) - to be in opposition; to be in private life",
  "野に隠れる": "(やにかくれる) - to retire from public service",
  "野の花": "(ののはな) - wild flowers",
  "野ぶどう": "(のぶどう) - wild grape; wild grapevine; ampelopsis"
}