{
  "ロゴ": "(ロゴ) - logo; logotype",
  "ロゴス": "(ロゴス) - logos",
  "ロゴセラピー": "(ロゴセラピー) - logotherapy",
  "ロゴタイプ": "(ロゴタイプ) - logotype",
  "ロゴマーク": "(ロゴ・マーク) - logo (wasei: logo mark)",
  "ロゴ・マーク": "(ロゴ・マーク) - logo (wasei: logo mark)",
  "ロサンジェルス": "(ロスアンゼルス) - Los Angeles",
  "ロサンゼルス": "(ロスアンゼルス) - Los Angeles",
  "ロザリオ": "(ロザリオ) - rosary (por: rosario)",
  "ロシアデスマン": "(ロシア・デスマン) - Russian desman (Desmana moschata)",
  "ロシアデスマン属": "(ロシアデスマンぞく) - Desmana; genus containing the Russian desman",
  "ロシアトルコ戦争": "(ロシアトルコせんそう) - Russo-Turkish War (1877-1878)",
  "ロシアンルーレット": "(ロシアンルーレット) - Russian roulette",
  "ロシア・デスマン": "(ロシア・デスマン) - Russian desman (Desmana moschata)",
  "ロシア五人組": "(ロシアごにんぐみ) - The Five (circle of Russian composers: Balakirev, Cui, Mussorgsky, Rimsky-Korsakov, and Borodin)",
  "ロシア人": "(ロシアじん) - Russian (person, people)",
  "ロシア共産党": "(ロシアきょうさんとう) - Russian Communist Party",
  "ロシア文字": "(ロシアもじ) - Russian character; Russian characters",
  "ロシア正教会": "(ロシアせいきょうかい) - Russian Orthodox Church",
  "ロシア語": "(ロシアご) - Russian (language)",
  "ロシア軍隊": "(ロシアぐんたい) - Russian army",
  "ロシア革命": "(ロシアかくめい) - Russian Revolution",
  "ロシス": "(ロシス) - LOCIS",
  "ロシニョール": "(ロシニョール) - Rossignol",
  "ロシュ限界": "(ロシュげんかい) - Roche limit; Roche's limit (closest that a natural satellite can come to the center of a planet without disintegrating due to tidal forces)",
  "ロジアナ": "(ロジアナ) - logic analyzer",
  "ロジウム": "(ロジウム) - rhodium (Rh)",
  "ロジカル": "(ロジカル) - logical",
  "ロジスティクス": "(ロジスティクス) - logistics",
  "ロジスティックス": "(ロジスティクス) - logistics",
  "ロジスティック分布": "(ロジスティックぶんぷ) - logistic distribution",
  "ロジスティック回帰": "(ロジスティックかいき) - logistic regression",
  "ロジスティック曲線": "(ロジスティックきょくせん) - logistic curve",
  "ロジック": "(ロジック) - logic",
  "ロジックアナライザ": "(ロジック・アナライザ) - logic analyser (analyzer)",
  "ロジックプログラミング": "(ロジック・プログラミング) - logic programming; logic programing",
  "ロジックボード": "(ロジック・ボード) - logic board",
  "ロジック・アナライザ": "(ロジック・アナライザ) - logic analyser (analyzer)",
  "ロジック・プログラミング": "(ロジック・プログラミング) - logic programming; logic programing",
  "ロジック・ボード": "(ロジック・ボード) - logic board",
  "ロジック回路": "(ロジックかいろ) - logic circuit",
  "ロジック爆弾": "(ロジックばくだん) - logic bomb",
  "ロジット": "(ロジット) - logit",
  "ロジバン": "(ロジバン) - Lojban (language)",
  "ロジン": "(ロジン) - rosin",
  "ロジンバッグ": "(ロジン・バッグ) - rosin bag",
  "ロジン・バッグ": "(ロジン・バッグ) - rosin bag",
  "ロス": "(ロス) - loss; feeling of loss; Los Angeles",
  "ロスアンゼルス": "(ロスアンゼルス) - Los Angeles",
  "ロスカット": "(ロス・カット) - loss-cutting (wasei: loss cut); cutting one's losses",
  "ロスジェネ": "(ロスジェネ) - lost generation",
  "ロスタイム": "(ロス・タイム) - loss of time; lost time",
  "ロスター": "(ロスター) - roster",
  "ロスト": "(ロスト) - lost; to lose",
  "ロストクラスタ": "(ロスト・クラスタ) - lost cluster",
  "ロストジェネレーション": "(ロスト・ジェネレーション) - lost generation",
  "ロストバージン": "(ロスト・ヴァージン) - losing one's virginity (wasei: lost virgin); defloration",
  "ロストボール": "(ロスト・ボール) - lost ball",
  "ロストヴァージン": "(ロスト・ヴァージン) - losing one's virginity (wasei: lost virgin); defloration",
  "ロスト・クラスタ": "(ロスト・クラスタ) - lost cluster",
  "ロスト・ジェネレーション": "(ロスト・ジェネレーション) - lost generation",
  "ロスト・バージン": "(ロスト・ヴァージン) - losing one's virginity (wasei: lost virgin); defloration",
  "ロスト・ボール": "(ロスト・ボール) - lost ball",
  "ロスト・ヴァージン": "(ロスト・ヴァージン) - losing one's virginity (wasei: lost virgin); defloration",
  "ロスマリン油": "(ロスマリンゆ) - rosemary oil",
  "ロスリーダー": "(ロス・リーダー) - loss leader",
  "ロスレス圧縮": "(ロスレスあっしゅく) - lossless compression",
  "ロス・カット": "(ロス・カット) - loss-cutting (wasei: loss cut); cutting one's losses",
  "ロス・タイム": "(ロス・タイム) - loss of time; lost time",
  "ロス・リーダー": "(ロス・リーダー) - loss leader",
  "ロス市警": "(ロスしけい) - Los Angeles police department; LAPD",
  "ロゼ": "(ローゼ) - rose (wine) (fre:); pink wine",
  "ロゼッタストーン": "(ロゼッタ・ストーン) - Rosetta Stone",
  "ロゼッタネット": "(ロゼッタネット) - rosettanet",
  "ロゼッタ・ストーン": "(ロゼッタ・ストーン) - Rosetta Stone",
  "ロゼッタ石": "(ロゼッタいし) - Rosetta stone",
  "ロゼット": "(ロゼット) - rosette",
  "ロゼワイン": "(ロゼ・ワイン) - rose (wine) (fre:); pink wine",
  "ロゼ・ワイン": "(ロゼ・ワイン) - rose (wine) (fre:); pink wine",
  "ロタウイルス": "(ロタウイルス) - rotavirus",
  "ロタンダ": "(ロトンダ) - rotunda",
  "ロチェスター": "(ロチェスター) - Rochester",
  "ロッカー": "(ロッカー) - locker; rocker",
  "ロッカールーム": "(ロッカー・ルーム) - locker room",
  "ロッカー・ルーム": "(ロッカー・ルーム) - locker room",
  "ロッカー室": "(ロッカーしつ) - locker room",
  "ロッキング": "(ロッキング) - rocking; locking",
  "ロッキングチェア": "(ロッキング・チェア) - rocking chair",
  "ロッキングモーション": "(ロッキング・モーション) - rocking motion",
  "ロッキング・チェア": "(ロッキング・チェア) - rocking chair",
  "ロッキング・モーション": "(ロッキング・モーション) - rocking motion",
  "ロッキード": "(ロッキード) - Lockheed",
  "ロッキード事件": "(ロッキードじけん) - Lockheed bribery scandal (uncovered in 1976)",
  "ロッキー山脈": "(ロッキーさんみゃく) - Rocky Mountains; the Rockies",
  "ロック": "(ロック) - lock; rock; roc",
  "ロックアウト": "(ロックアウト) - lockout; protection",
  "ロックアウト機能": "(ロックアウトきのう) - lock-out facility",
  "ロックウール": "(ロック・ウール) - rock wool",
  "ロックガーデン": "(ロック・ガーデン) - rock garden",
  "ロッククライミング": "(ロッククライミング) - rock-climbing"
}