{
  "往生際の悪い": "(おうじょうぎわのわるい) - unreasonably stubborn; not knowing when to give up",
  "往者": "(おうしゃ) - person going (away); past",
  "往航": "(おうこう) - outward voyage",
  "往訪": "(おうほう) - visit; interview",
  "往診": "(おうしん) - doctor's visit; house call",
  "往路": "(おうろ) - outward journey",
  "往返": "(おうへん) - round trip",
  "往還": "(おうかん) - traffic; coming and going; highway",
  "征く": "(ゆく) - to conquer; to subjugate",
  "征する": "(せいする) - to conquer; to subjugate; to overcome",
  "征伐": "(seibatsu) - conquista, subjugação, superação; castigo, punição, expedição punitiva",
  "征圧": "(せいあつ) - conquest; subjugation; overcoming; controlling",
  "征夷": "(せいい) - warring against barbarians",
  "征夷大将軍": "(せいいたいしょうぐん) - commander-in-chief of the expeditionary force against the barbarians; great, unifying leader",
  "征戦": "(せいせん) - military expedition",
  "征服": "(seifuku) - conquista, subjugação, superação",
  "征服欲": "(せいふくよく) - the lust for conquest",
  "征服者": "(せいふくしゃ) - conqueror",
  "征矢": "(そや) - used arrow, collected from battlefield",
  "征箭": "(そや) - used arrow, collected from battlefield",
  "征衣": "(せいい) - traveling clothes; travelling clothes; military uniform",
  "征討": "(せいとう) - subjugation; conquest",
  "征途": "(せいと) - (military or pleasure) expedition",
  "征途に上る": "(せいとにのぼる) - to start on a journey; to go on a military expedition",
  "征露": "(せいろ) - (term used primarily during the Russo-Japanese war)  attacking Russia",
  "征露丸": "(せいろがん) - seirogan; beechwood extract popular as a herbal treatment for diarrhoea (diarrhea), etc.",
  "征韓論": "(せいかんろん) - policy of conquering Korea by military force",
  "径": "(kei) - diâmetro",
  "径の大きい": "(けいのおおきい) - of large diameter",
  "径庭": "(けいてい) - great difference",
  "径行": "(けいこう) - going right ahead",
  "径路": "(けいろ) - course/route/path/channel; process/means",
  "径路係数": "(けいろけいすう) - path coefficient",
  "径間": "(わたりま) - distance between two points; distance between opposite supports of arch, bridge; span",
  "待たす": "(またす) - to keep (a person) waiting",
  "待たせる": "(またせる) - to keep (a person) waiting",
  "待ち": "(machi) - espera, tempo de espera; espera por uma peça, peça que completaria a mão de alguém",
  "待ちあわせ": "(まちあわせ) - appointment",
  "待ちあわせる": "(まちあわせる) - to rendezvous; to meet at a prearranged place and time; to arrange to meet",
  "待ちうけ画面": "(まちうけがめん) - standby screen; standby display",
  "待ちかね": "(まちかね) - long-waited-for",
  "待ちかまえる": "(まちかまえる) - to lie in wait; to be on the watch for",
  "待ちくたびれる": "(まちくたびれる) - to get tired of waiting",
  "待ちこがれる": "(まちこがれる) - to long for",
  "待ちどうしい": "(まちどおしい) - looking forward to; anxiously awaited",
  "待ちに待った": "(まちにまった) - long-awaited; eagerly awaited",
  "待ちに待つ": "(まちにまつ) - to wait for a long time; to wait and wait; to eagerly await",
  "待ちぼうけ": "(まちぼうけ) - waiting in vain",
  "待ちぼうけを食う": "(まちぼうけをくう) - to go on waiting only to be disappointed; to wait in vain",
  "待ちわびる": "(まちわびる) - to be tired of waiting; to wait impatiently",
  "待ち人": "(まちびと) - person being waited for; person who waits",
  "待ち伏せ": "(まちぶせ) - performing an ambush",
  "待ち伏せる": "(まちぶせる) - to ambush",
  "待ち佗びる": "(まちわびる) - to be tired of waiting; to wait impatiently",
  "待ち侘びる": "(まちわびる) - to be tired of waiting; to wait impatiently",
  "待ち倦む": "(まちあぐむ) - to tire of waiting",
  "待ち兼ね": "(まちかね) - long-waited-for",
  "待ち兼ねる": "(まちかねる) - to wait impatiently for",
  "待ち切れない": "(まちきれない) - waiting impatiently for",
  "待ち受ける": "(まちうける) - to await; to expect",
  "待ち受け画像": "(まちうけがぞう) - stand by image (on mobile phones)",
  "待ち受け画面": "(まちうけがめん) - standby screen; standby display",
  "待ち合い": "(まちあい) - meeting place/assignation place; geisha entertaining room/teahouse/machiai",
  "待ち合せる": "(まちあわせる) - to rendezvous; to meet at a prearranged place and time; to arrange to meet",
  "待ち合わせ": "(まちあわせ) - appointment",
  "待ち合わせる": "(まちあわせる) - to rendezvous; to meet at a prearranged place and time; to arrange to meet",
  "待ち合わせ場所": "(まちあわせばしょ) - meeting place",
  "待ち惚け": "(まちぼうけ) - waiting in vain",
  "待ち惚ける": "(まちぼける) - to wait in vain",
  "待ち明かす": "(まちあかす) - to wait all night",
  "待ち時間": "(まちじかん) - waiting time; latency; standby time (e.g. cellular phones)",
  "待ち暮らす": "(まちくらす) - to wait all day",
  "待ち望む": "(まちのぞむ) - to look anxiously for; to wait eagerly for",
  "待ち構える": "(まちかまえる) - to lie in wait; to be on the watch for",
  "待ち焦がれる": "(まちこがれる) - to long for",
  "待ち状態": "(まちじょうたい) - waiting state",
  "待ち行列": "(まちぎょうれつ) - queue; pushup list",
  "待ち行列に入れる": "(まちぎょうれつにいれる) - to enqueue",
  "待ち行列名": "(まちぎょうれつめい) - queue name",
  "待ち行列方式": "(まちぎょうれつほうしき) - queue-driven",
  "待ち行列理論": "(まちぎょうれつりろん) - queueing theory",
  "待ち設ける": "(まちもうける) - to expect; to look for; to look forward to; to anticipate; to wait for",
  "待ち詫びる": "(まちわびる) - to be tired of waiting; to wait impatiently",
  "待ち遠しい": "(まちどおしい) - looking forward to; anxiously awaited",
  "待ち針": "(まちばり) - marking pin",
  "待ち駒": "(まちごま) - {shogi} anticipating the escape of the king and blocking him in advance with a knight",
  "待った": "(まった) - {sumo} false start of a bout; backsies (called when taking back a move in a game)",
  "待ったなし": "(まったなし) - now or never; time's up",
  "待ったなしの状況": "(まったなしのじょうきょう) - urgent state of affairs; pressing situation",
  "待ったをかける": "(まったをかける) - to put a stop to; to put a hold on; to put the brakes on; to call a halt to; to block; to shelve",
  "待ったを掛ける": "(まったをかける) - to put a stop to; to put a hold on; to put the brakes on; to call a halt to; to block; to shelve",
  "待った無し": "(まったなし) - now or never; time's up",
  "待つ": "(matsu) - esperar; aguardar, ansiar, antecipar; depender de, precisar",
  "待つ身は長い": "(まつみはながい) - A watched pot never boils",
  "待てど暮せど": "(まてどくらせど) - I waited a long time, but ...",
  "待てど暮らせど": "(まてどくらせど) - I waited a long time, but ...",
  "待てば海路の日和有り": "(まてばかいろのひよりあり) - Everything comes to him who waits",
  "待人": "(まちびと) - person being waited for; person who waits",
  "待伏せ": "(まちぶせ) - performing an ambush",
  "待伏せる": "(まちぶせる) - to ambush"
}