{
  "ダイアルアップ": "(ダイアル・アップ) - dial-up (esp. modem connection)",
  "ダイアルアップ接続": "(ダイアルアップせつぞく) - dial-up connection",
  "ダイアルアップＩＰ接続": "(ダイアルアップアイピーせつぞく) - dial-up IP connection",
  "ダイアルイン": "(ダイアル・イン) - direct telephone number (wasei: dial in)",
  "ダイアル・アップ": "(ダイアル・アップ) - dial-up (esp. modem connection)",
  "ダイアル・イン": "(ダイアル・イン) - direct telephone number (wasei: dial in)",
  "ダイアル式": "(ダイアルしき) - dial-style (e.g. of phones)",
  "ダイアレクト": "(ダイヤレクト) - dialect",
  "ダイアログ": "(ダイアローグ) - dialogue; dialog",
  "ダイアログボックス": "(ダイアログ・ボックス) - dialog box",
  "ダイアログボックスを閉じる": "(ダイアログボックスをとじる) - to dismiss a dialog box",
  "ダイアログ・ボックス": "(ダイアログ・ボックス) - dialog box",
  "ダイアログ回復": "(ダイアログかいふく) - dialogue recovery",
  "ダイアログ確立指示未完了": "(ダイアログかくりつしじみかんりょう) - dialogue establishment indication outstanding",
  "ダイアログ確立要求未完了": "(ダイアログかくりつようきゅうみかんりょう) - dialogue establishment request outstanding",
  "ダイアログ終了指示未完了": "(ダイアログしゅうりょうしじみかんりょう) - dialogue termination indication outstanding",
  "ダイアログ終了要求未完了": "(ダイアログしゅうりょうようきゅうみかんりょう) - dialogue termination request outstanding",
  "ダイアローグ": "(ダイアローグ) - dialogue; dialog",
  "ダイア・ウルフ": "(ダイア・ウルフ) - dire wolf (extinct, Canis dirus)",
  "ダイイン": "(ダイイン) - diein",
  "ダイエット": "(ダイエット) - diet; losing weight by any method (e.g. exercise)",
  "ダイエットふりかけ": "(ダイエットふりかけ) - furikake put on rice to make it blue, which is said to act as an appetite suppressant",
  "ダイオキシン": "(ダイオキシン) - dioxin",
  "ダイオキシン汚染": "(ダイオキシンおせん) - dioxin contamination",
  "ダイオキシン法施行規則": "(ダイオキシンほうしこうきそく) - Law Concerning Special Measures Against Dioxins",
  "ダイオド": "(ダイオド) - diode",
  "ダイオード": "(ダイオド) - diode",
  "ダイオードトランジスタ論理回路": "(ダイオードトランジスタろんりかいろ) - Diode-Transistor Logic",
  "ダイオード関数発生器": "(ダイオードかんすうはっせいき) - Diode Function Generator; DFG",
  "ダイカスト": "(ダイカスト) - die casting",
  "ダイカー": "(ダイカー) - duiker (Cephalophinae); duyker",
  "ダイキャスト": "(ダイカスト) - die casting",
  "ダイキリ": "(ダイキリ) - daiquiri",
  "ダイクストラ": "(ダイクストラ) - Dijkstra",
  "ダイクロイックミラー": "(ダイクロイックミラー) - dichroic mirror",
  "ダイコン": "(ダイコン) - dive computer",
  "ダイサ": "(ダイサ) - DISA",
  "ダイサイズ": "(ダイ・サイズ) - die size",
  "ダイシング": "(ダイシング) - dicing (e.g. cutting up of a microchip wafer)",
  "ダイジェスト": "(ダイジェスト) - digest",
  "ダイジェストアクセスプロトコル": "(ダイジェストアクセスプロトコル) - digest access protocol",
  "ダイス": "(ダイス) - dice; die (tool)",
  "ダイス回し": "(ダイスまわし) - diestock; die handle",
  "ダイダラボッチ": "(ダイダラボッチ) - mythical giant",
  "ダイトクベニハゼ": "(ダイトクベニハゼ) - Trimma caudipunctatum (species of goby found in Japan and Palau)",
  "ダイナセット": "(ダイナセット) - dynamic set",
  "ダイナブック": "(ダイナブック) - DynaBook",
  "ダイナマイト": "(ダイナマイト) - dynamite",
  "ダイナミクス": "(ダイナミクス) - dynamics",
  "ダイナミサイザ": "(ダイナミサイザ) - serializer; parallel-serial converter; dynamicizer",
  "ダイナミズム": "(ダイナミズム) - dynamism",
  "ダイナミック": "(ダイナミック) - dynamic",
  "ダイナミックアロケーション": "(ダイナミック・アロケーション) - dynamic allocation",
  "ダイナミックス": "(ダイナミックス) - dynamics",
  "ダイナミックスピーカー": "(ダイナミック・スピーカー) - dynamic speaker",
  "ダイナミックディスク": "(ダイナミック・ディスク) - dynamic disk",
  "ダイナミックデータエクスチェンジ": "(ダイナミック・データ・エクスチェンジ) - dynamic data exchange; DDE",
  "ダイナミックプログラミング": "(ダイナミック・プログラミング) - dynamic programming",
  "ダイナミックメモリ": "(ダイナミック・メモリ) - dynamic memory",
  "ダイナミックリロケーション": "(ダイナミック・リロケーション) - dynamic relocation",
  "ダイナミックリンク": "(ダイナミック・リンク) - dynamic link",
  "ダイナミックリンクライブラリ": "(ダイナミック・リンク・ライブラリ) - dynamic linking library; DLL",
  "ダイナミックリンクライブラリファイル": "(ダイナミック・リンク・ライブラリ・ファイル) - dynamic-link library file",
  "ダイナミックルーティング": "(ダイナミック・ルーティング) - dynamic routing",
  "ダイナミックルート": "(ダイナミック・ルート) - dynamic route",
  "ダイナミックレンジ": "(ダイナミック・レンジ) - dynamic range",
  "ダイナミック・アロケーション": "(ダイナミック・アロケーション) - dynamic allocation",
  "ダイナミック・スピーカー": "(ダイナミック・スピーカー) - dynamic speaker",
  "ダイナミック・ディスク": "(ダイナミック・ディスク) - dynamic disk",
  "ダイナミック・データ・エクスチェンジ": "(ダイナミック・データ・エクスチェンジ) - dynamic data exchange; DDE",
  "ダイナミック・プログラミング": "(ダイナミック・プログラミング) - dynamic programming",
  "ダイナミック・メモリ": "(ダイナミック・メモリ) - dynamic memory",
  "ダイナミック・リロケーション": "(ダイナミック・リロケーション) - dynamic relocation",
  "ダイナミック・リンク": "(ダイナミック・リンク) - dynamic link",
  "ダイナミック・リンク・ライブラリ": "(ダイナミック・リンク・ライブラリ) - dynamic linking library; DLL",
  "ダイナミック・リンク・ライブラリ・ファイル": "(ダイナミック・リンク・ライブラリ・ファイル) - dynamic-link library file",
  "ダイナミック・ルーティング": "(ダイナミック・ルーティング) - dynamic routing",
  "ダイナミック・ルート": "(ダイナミック・ルート) - dynamic route",
  "ダイナミック・レンジ": "(ダイナミック・レンジ) - dynamic range",
  "ダイナミックＨＴＭＬ": "(ダイナミックエッチティーエムエル) - dynamic HTML",
  "ダイナミックＲＡＭ": "(ダイナミックラム) - dynamic Random Access Memory (dynamic RAM, DRAM)",
  "ダイナモ": "(ダイナモ) - dynamo",
  "ダイナモザイク": "(ダイナモザイク) - DynaMosaic",
  "ダイナモメーター": "(ダイナモメーター) - dynamometer",
  "ダイナモ理論": "(ダイナモりろん) - dynamo theory",
  "ダイナー": "(ダイナー) - diner",
  "ダイナースクラブ": "(ダイナース・クラブ) - Diner's Club (credit card)",
  "ダイナース・クラブ": "(ダイナース・クラブ) - Diner's Club (credit card)",
  "ダイニング": "(ダイニング) - dining; dining room; meal",
  "ダイニングキッチン": "(ダイニング・キッチン) - eat-in kitchen (wasei: dining kitchen)",
  "ダイニングテーブル": "(ダイニング・テーブル) - dining table",
  "ダイニングルーム": "(ダイニング・ルーム) - dining room",
  "ダイニング・キッチン": "(ダイニング・キッチン) - eat-in kitchen (wasei: dining kitchen)",
  "ダイニング・テーブル": "(ダイニング・テーブル) - dining table",
  "ダイニング・ルーム": "(ダイニング・ルーム) - dining room",
  "ダイノソア": "(ディノサウル) - dinosaur",
  "ダイノソー": "(ディノサウル) - dinosaur",
  "ダイハツ": "(ダイハツ) - Daihatsu (Japanese automobile manufacturer)",
  "ダイバー": "(ダイバー) - diver",
  "ダイバーシティ": "(ダイバーシティ) - diversity"
}