{
  "サービスマーク": "(サービス・マーク) - service mark",
  "サービスヤード": "(サービス・ヤード) - service yard",
  "サービスライン": "(サービス・ライン) - service line",
  "サービスルーチン": "(サービス・ルーチン) - utility routine; service routine",
  "サービスルーチンプログラム": "(サービスルーチンプログラム) - utility routine (program); service routine (program)",
  "サービスルーム": "(サービス・ルーム) - service room",
  "サービスレベル": "(サービス・レベル) - service level",
  "サービスロード": "(サービス・ロード) - service load",
  "サービス・アクセス・ポイント": "(サービス・アクセス・ポイント) - service access point; SAP",
  "サービス・アスペクト": "(サービス・アスペクト) - service aspect",
  "サービス・エリア": "(サービス・エリア) - service area (usu. an area off a highway to buy gasoline, etc. for vehicles)",
  "サービス・エンドポイント": "(サービス・エンドポイント) - service end point",
  "サービス・エース": "(サービス・エース) - ace (tennis) (wasei: service ace)",
  "サービス・カー": "(サービス・カー) - service car",
  "サービス・ガール": "(サービス・ガール) - waitress (wasei: service girl); (restaurant) host",
  "サービス・クラス": "(サービス・クラス) - service class",
  "サービス・グレード": "(サービス・グレード) - service grade",
  "サービス・コンセント": "(サービス・コンセント) - service outlet",
  "サービス・コート": "(サービス・コート) - service court",
  "サービス・サイズ": "(サービス・サイズ) - service size",
  "サービス・ステイション": "(サービス・ステイション) - service station",
  "サービス・ステーション": "(サービス・ステイション) - service station",
  "サービス・センター": "(サービス・センター) - service center",
  "サービス・タイプ": "(サービス・タイプ) - service type",
  "サービス・タイム": "(サービス・タイム) - happy hour (wasei: service time)",
  "サービス・ハウス": "(サービス・ハウス) - service house",
  "サービス・ビューロー": "(サービス・ビューロー) - Service Bureau",
  "サービス・ブレーク": "(サービス・ブレーク) - service break",
  "サービス・プリミティブ": "(サービス・プリミティブ) - service primitive",
  "サービス・プログラム": "(サービス・プログラム) - utility program; service program",
  "サービス・プロバイダ": "(サービス・プロバイダ) - service provider",
  "サービス・マーク": "(サービス・マーク) - service mark",
  "サービス・ヤード": "(サービス・ヤード) - service yard",
  "サービス・ライン": "(サービス・ライン) - service line",
  "サービス・ルーチン": "(サービス・ルーチン) - utility routine; service routine",
  "サービス・ルーム": "(サービス・ルーム) - service room",
  "サービス・レベル": "(サービス・レベル) - service level",
  "サービス・ロード": "(サービス・ロード) - service load",
  "サービス不能攻撃": "(サービスふのうこうげき) - denial of service attack",
  "サービス付き": "(サービスつき) - serviced; service-included",
  "サービス付き高齢者向け住宅": "(サービスつきこうれいしゃむけじゅうたく) - housing for the elderly with home-care services provided",
  "サービス便覧": "(サービスびんらん) - user handbook; service handbook",
  "サービス信頼性": "(サービスしんらいせい) - service reliability",
  "サービス内容": "(サービスないよう) - description of services offered; service content",
  "サービス制御群": "(サービスせいぎょぐん) - service controls",
  "サービス品質": "(サービスひんしつ) - quality of service; QOS",
  "サービス品質契約": "(サービスひんしつけいやく) - quality of service agreement, contract",
  "サービス妨害攻撃": "(サービスぼうがいこうげき) - denial of service attack",
  "サービス実現": "(サービスじつげん) - service implementation",
  "サービス拒否攻撃": "(サービスきょひこうげき) - denial of service attack",
  "サービス提供区域": "(サービスていきょうくいき) - service area boundary",
  "サービス提供地域": "(サービスていきょうちいき) - service area",
  "サービス提供者": "(サービスていきょうしゃ) - service provider",
  "サービス料": "(サービスりょう) - service charge",
  "サービス料金": "(サービスりょうきん) - service charge",
  "サービス業": "(サービスぎょう) - service industry; service sector",
  "サービス残業": "(サービスざんぎょう) - unpaid overtime",
  "サービス産業": "(サービスさんぎょう) - service industry; service sector",
  "サービス種別": "(サービスしゅべつ) - service class",
  "サービス統合ディジタル網": "(サービスとうごうディジタルもう) - ISDN; integrated services digital network",
  "サービス要素": "(サービスようそ) - element of service; service element",
  "サービス部門": "(サービスぶもん) - service sector; tertiary sector",
  "サーフ": "(サーフ) - surf",
  "サーファー": "(サーファー) - surfer",
  "サーフィス": "(サーフィス) - surface",
  "サーフィスモデル": "(サーフェス・モデル) - surface model",
  "サーフィス・モデル": "(サーフェス・モデル) - surface model",
  "サーフィン": "(サーフィン) - surfing",
  "サーフェイス": "(サーフィス) - surface",
  "サーフェイスモデル": "(サーフェス・モデル) - surface model",
  "サーフェイス・モデル": "(サーフェス・モデル) - surface model",
  "サーフェス": "(サーフィス) - surface",
  "サーフェスモデル": "(サーフェス・モデル) - surface model",
  "サーフェス・モデル": "(サーフェス・モデル) - surface model",
  "サーフキャスティング": "(サーフ・キャスティング) - surf casting",
  "サーフキャスト": "(サーフ・キャスト) - surf cast",
  "サーフジェット": "(サーフ・ジェット) - surf jet",
  "サーフスキー": "(サーフ・スキー) - surf ski",
  "サーフトローリング": "(サーフトローリング) - surf trolling",
  "サーフパンツ": "(サーフ・パンツ) - surf pants",
  "サーフボード": "(サーフボード) - surfboard",
  "サーフミュージック": "(サーフ・ミュージック) - surf music",
  "サーフライダー": "(サーフ・ライダー) - surf rider",
  "サーフローラー": "(サーフ・ローラー) - surf roller",
  "サーフ・キャスティング": "(サーフ・キャスティング) - surf casting",
  "サーフ・キャスト": "(サーフ・キャスト) - surf cast",
  "サーフ・ジェット": "(サーフ・ジェット) - surf jet",
  "サーフ・スキー": "(サーフ・スキー) - surf ski",
  "サーフ・パンツ": "(サーフ・パンツ) - surf pants",
  "サーフ・ミュージック": "(サーフ・ミュージック) - surf music",
  "サーフ・ライダー": "(サーフ・ライダー) - surf rider",
  "サーフ・ローラー": "(サーフ・ローラー) - surf roller",
  "サーブ": "(サーブ) - serve",
  "サーブアンドボレー": "(サーブ・アンド・ボレー) - serve and volley",
  "サーブポイント": "(サーブ・ポイント) - serve point",
  "サーブル": "(サーブル) - (サーブル is usu. in fencing; サーベル in cavalry) sabre (fre:, dut: sabel); saber",
  "サーブレット": "(サーブレット) - servlet",
  "サーブ・アンド・ボレー": "(サーブ・アンド・ボレー) - serve and volley",
  "サーブ・ポイント": "(サーブ・ポイント) - serve point",
  "サープラス": "(サープラス) - surplus"
}