{
  "プランジャー・ポンプ": "(プランジャー・ポンプ) - plunger pump",
  "プランタン": "(プリンタン) - springtime (fre: printemps); spring",
  "プランター": "(プランター) - planter",
  "プランテーション": "(プランテーション) - plantation",
  "プラント": "(プラント) - plant (i.e. equipment, machinery, etc.)",
  "プラントオパール": "(プラント・オパール) - plant opal (opal phytolith)",
  "プラントリノベーション": "(プラント・リノベーション) - plant renovation",
  "プラントレイアウト": "(プラント・レイアウト) - plant layout",
  "プラント・オパール": "(プラント・オパール) - plant opal (opal phytolith)",
  "プラント・リノベーション": "(プラント・リノベーション) - plant renovation",
  "プラント・レイアウト": "(プラント・レイアウト) - plant layout",
  "プラント輸出": "(プラントゆしゅつ) - export of manufacturing plant",
  "プランナー": "(プランナー) - planner; game designer",
  "プランニング": "(プランニング) - planning",
  "プラークリット語": "(プラークリットご) - Prakrit (language)",
  "プラーグ": "(プラーグ) - Prague",
  "プラーザ": "(プラーザ) - plaza",
  "プラージュ": "(プラージュ) - plage",
  "プリ": "(プリ) - pre-",
  "プリアンブル": "(プリアンブル) - preamble",
  "プリアンプ": "(プリアンプ) - pre-amplifier",
  "プリインストール": "(プリインストール) - preinstall",
  "プリインストールソフトウェア": "(プリインストール・ソフトウェア) - preinstalled software",
  "プリインストール・ソフトウェア": "(プリインストール・ソフトウェア) - preinstalled software",
  "プリウス": "(プリウス) - (Toyota) Prius",
  "プリエンプティブ": "(プリエンプティブ) - preemptive",
  "プリエンプティブなマルチタスク": "(プリエンプティブなマルチタスク) - preemptive multitasking",
  "プリエンプティブマルチタスク": "(プリエンプティブ・マルチタスク) - preemptive multitasking",
  "プリエンプティブ・マルチタスク": "(プリエンプティブ・マルチタスク) - preemptive multitasking",
  "プリエンプティブ式のマルチタスキング": "(プリエンプティブしきのマルチタスキング) - preemptive multitasking",
  "プリオン": "(プリオン) - prion",
  "プリオン病": "(プリオンびょう) - {med}  prion disease",
  "プリクラ": "(プリクラ) - photo booth that prints out cards and stickers of the resulting photograph, which are then traded among friends (wasei: print club)",
  "プリザーブド": "(プリザーブド) - preserved (e.g. flower)",
  "プリザーブドフラワー": "(プリザーブド・フラワー) - preserved flower",
  "プリザーブド・フラワー": "(プリザーブド・フラワー) - preserved flower",
  "プリステラ": "(プリステラ) - pristella tetra (Pristella maxillaris) (lat: Pristella); X-ray tetra",
  "プリズム": "(プリズム) - prism",
  "プリズン": "(プリズン) - prison",
  "プリセット": "(プリセット) - preset",
  "プリセット値": "(プリセットあたい) - preset value",
  "プリセール": "(プリセール) - presale; pre-sale; advance sale",
  "プリチャージ": "(プリチャージ) - precharge",
  "プリティ": "(プリティー) - pretty",
  "プリティプリント": "(プリティプリント) - pretty-print",
  "プリティー": "(プリティー) - pretty",
  "プリトラ": "(プリトラ) - pre-translation",
  "プリナップ": "(プレナップ) - prenuptial agreement; prenup",
  "プリファレンス": "(プリファレンス) - preference",
  "プリフィクス": "(プリフィクス) - prefix",
  "プリフェッチ": "(プリフェッチ) - prefetch",
  "プリプリ": "(ぶりぶり) - angrily/in a huff/in anger; high on marijuana; (プリプリ, ぷりぷり only) tender (to chew)",
  "プリプリ怒る": "(プリプリおこる) - to be in a huff",
  "プリプロセッサ": "(プリプロセッサー) - preprocessor",
  "プリプロセッサー": "(プリプロセッサー) - preprocessor",
  "プリプロダクション": "(プリ・プロダクション) - pre-production (film)",
  "プリベータ": "(プリベータ) - pre-beta",
  "プリペアードピアノ": "(プリペアード・ピアノ) - prepared piano",
  "プリペアード・ピアノ": "(プリペアード・ピアノ) - prepared piano",
  "プリペイド": "(プリペード) - prepaid (phone, card, etc.)",
  "プリペイドカード": "(プリペイド・カード) - prepaid card",
  "プリペイドテレフォンカード": "(プリペイド・テレフォン・カード) - prepaid telephone card",
  "プリペイド・カード": "(プリペイド・カード) - prepaid card",
  "プリペイド・テレフォン・カード": "(プリペイド・テレフォン・カード) - prepaid telephone card",
  "プリペイド式携帯電話": "(プリペイドしきけいたいでんわ) - prepaid cellphone",
  "プリペード": "(プリペード) - prepaid (phone, card, etc.)",
  "プリマ": "(プリマ) - prima donna (ita:)",
  "プリマスロック": "(プリマス・ロック) - Plymouth Rock (breed of chicken)",
  "プリマス・ロック": "(プリマス・ロック) - Plymouth Rock (breed of chicken)",
  "プリマドンナ": "(プリマ・ドンナ) - prima donna (ita:)",
  "プリマバレリーナ": "(プリマバレリーナ) - prima ballerina (ita:)",
  "プリマ・ドンナ": "(プリマ・ドンナ) - prima donna (ita:)",
  "プリミチブ": "(プリミティヴ) - primitive; crude; archaic",
  "プリミティブ": "(プリミティヴ) - primitive; crude; archaic",
  "プリミティブアート": "(プリミティブ・アート) - primitive art",
  "プリミティブ・アート": "(プリミティブ・アート) - primitive art",
  "プリミティヴ": "(プリミティヴ) - primitive; crude; archaic",
  "プリムラ": "(プリムラ) - primula (any flower of genus Primula, which includes primroses, cowslips and cyclamens)",
  "プリムローズ": "(プリムローズ) - primrose",
  "プリューム": "(プリューム) - plume",
  "プリレコーディング": "(プリレコーディング) - prerecording",
  "プリレンダ": "(プリレンダ) - pre-render; pre-rendering",
  "プリン": "(プリン) - (custard) pudding; purine",
  "プリンキピア": "(プリンキピア) - Philosophiae Naturalis Principia Mathematica (physical science treatise by Sir Isaac Newton, 1687) (lat:)",
  "プリンシパル": "(プリンシパル) - principal",
  "プリンシプル": "(プリンシプル) - principle",
  "プリンス": "(プリンス) - prince",
  "プリンスメロン": "(プリンス・メロン) - prince melon",
  "プリンス・メロン": "(プリンス・メロン) - prince melon",
  "プリンセス": "(プリンセス) - princess",
  "プリンセスコート": "(プリンセス・コート) - princess coat",
  "プリンセスライン": "(プリンセス・ライン) - princess line",
  "プリンセス・コート": "(プリンセス・コート) - princess coat",
  "プリンセス・ライン": "(プリンセス・ライン) - princess line",
  "プリンタ": "(プリンタ) - printer",
  "プリンタウィンドウ": "(プリンタ・ウィンドウ) - printer window",
  "プリンタエンジン": "(プリンタ・エンジン) - printer engine",
  "プリンタケーブル": "(プリンタ・ケーブル) - printer cable",
  "プリンタコネクタ": "(プリンタ・コネクタ) - printer connector",
  "プリンタセッション": "(プリンタ・セッション) - printer session"
}